apies/VERSION
apies/__init__.py
apies/blueprint.py
apies/controllers.py
apies/logger.py
apies/query.py
apies/sources.py
apies/utils/__init__.py
apies/utils/file_maker.py
apies-1.13.1.dist-info/LICENSE
apies-1.13.1.dist-info/METADATA
apies-1.13.1.dist-info/WHEEL
apies-1.13.1.dist-info/top_level.txt
apies-1.13.1.dist-info/RECORD
