Metadata-Version: 2.1
Name: apies
Version: 1.13.1
Summary: A flask blueprint providing an API for accessing and searching an ElasticSearch index created from source datapackages
Home-page: https://github.com/OpenBudget/apies
Author: Adam Kariv
Author-email: adam.kariv@gmail.com
License: MIT
Keywords: data
Classifier: Development Status :: 4 - Beta
Classifier: Intended Audience :: Developers
Classifier: License :: OSI Approved :: MIT License
Classifier: Operating System :: OS Independent
Classifier: Programming Language :: Python :: 3.6
Classifier: Topic :: Software Development :: Libraries :: Python Modules
License-File: LICENSE
Requires-Dist: Flask
Requires-Dist: requests
Requires-Dist: elasticsearch <9.0.0,>=7.0.0
Requires-Dist: datapackage
Requires-Dist: flask-jsonpify
Requires-Dist: demjson3
Requires-Dist: xlwt
Requires-Dist: xlsxwriter
Provides-Extra: develop
Requires-Dist: pylama ; extra == 'develop'
Requires-Dist: tox ; extra == 'develop'
Requires-Dist: dataflows-elasticsearch >=0.1.0 ; extra == 'develop'
